fastapi_exts/__init__.py
fastapi_exts/_utils.py
fastapi_exts/dependencies.py
fastapi_exts/exceptions.py
fastapi_exts/fields.py
fastapi_exts/interfaces.py
fastapi_exts/lifespan.py
fastapi_exts/logger.py
fastapi_exts/models.py
fastapi_exts/pagination.py
fastapi_exts/provider.py
fastapi_exts/py.typed
fastapi_exts/responses.py
fastapi_exts/servers.py
fastapi_exts/url_path.py
fastapi_exts/utils.py
fastapi_exts/cbv/__init__.py
fastapi_exts/cbv/_utils.py
fastapi_exts/cbv/base.py
fastapi_exts/routing/__init__.py
fastapi_exts/routing/utils.py
fastapi_exts/sqlalchemy/__init__.py
fastapi_exts/sqlalchemy/mixins.py
fastapi_exts/sqlalchemy/pagination.py
fastapi_exts/sqlalchemy/session.py
fastapi_exts-0.2.8.dist-info/METADATA
fastapi_exts-0.2.8.dist-info/WHEEL
fastapi_exts-0.2.8.dist-info/RECORD
