Metadata-Version: 2.4
Name: fastapi-exts
Version: 0.2.8
Summary: Add your description here
Author-email: nafnix <uwu@nafnix.com>
Requires-Python: >=3.11
Requires-Dist: fastapi>=0.115.12
